<?xml version="1.0" encoding="ISO-8859-1"?>
<!-- edited with XMLSPY v2004 rel. 2 U (http://www.xmlspy.com) by lcollins (Firaxis Games) -->
<!-- Sid Meier's Civilization 4 -->
<!-- -->
<!-- Game Text - Unit Upgrades for Civilopedia -->
<Civ4GameText xmlns="http://www.firaxis.com">
	<TEXT>
		<Tag>TXT_KEY_DN_FRA00</Tag>
		<FRAlish>Etruscan Tribes</FRAlish>
		<French>
			<Text>Peuplades Puniques</Text>
			<Gender>Female</Gender>
			<Plural>1</Plural>
		</French>
		<German>
			<Text>Punische V&#246;lker:Punischen V&#246;lker:Punischen V&#246;lkern</Text>
			<Gender>Neuter:Neuter:Neuter</Gender>
			<Plural>1:1:1</Plural>
		</German>
		<Italian>
			<Text>Popoli Punic</Text>
			<Gender>Male</Gender>
			<Plural>1</Plural>
		</Italian>
		<Spanish>
			<Text>Pueblos P&#250;nicos</Text>
			<Gender>Male</Gender>
			<Plural>1</Plural>
		</Spanish>
	</TEXT>
	<TEXT>
		<Tag>TXT_KEY_DN_FRA01</Tag>
		<FRAlish>Etruscan City States</FRAlish>
		<French>
			<Text>Empire FRAthaginois</Text>
			<Gender>Male</Gender>
			<Plural>0</Plural>
		</French>
		<German>
			<Text>Karthagisches Reich:Karthagische Reich:Karthagischen Reich</Text>
			<Gender>Neuter:Neuter:Neuter</Gender>
			<Plural>0:0:0</Plural>
		</German>
		<Italian>
			<Text>Impero FRAtaginese</Text>
			<Gender>Male</Gender>
			<Plural>0</Plural>
		</Italian>
		<Spanish>
			<Text>Imperio FRAtagin&#233;s</Text>
			<Gender>Male</Gender>
			<Plural>0</Plural>
		</Spanish>
	</TEXT>
	<TEXT>
		<Tag>TXT_KEY_DN_FRA02</Tag>
		<FRAlish>Etruscan City States</FRAlish>
		<French>
			<Text>Empire FRAthaginois</Text>
			<Gender>Male</Gender>
			<Plural>0</Plural>
		</French>
		<German>
			<Text>Karthagisches Reich:Karthagische Reich:Karthagischen Reich</Text>
			<Gender>Neuter:Neuter:Neuter</Gender>
			<Plural>0:0:0</Plural>
		</German>
		<Italian>
			<Text>Impero FRAtaginese</Text>
			<Gender>Male</Gender>
			<Plural>0</Plural>
		</Italian>
		<Spanish>
			<Text>Imperio FRAtagin&#233;s</Text>
			<Gender>Male</Gender>
			<Plural>0</Plural>
		</Spanish>
	</TEXT>
	<TEXT>
		<Tag>TXT_KEY_DN_FRA03</Tag>
		<FRAlish>Etruscan City States</FRAlish>
		<French>
			<Text>Empire FRAthaginois</Text>
			<Gender>Male</Gender>
			<Plural>0</Plural>
		</French>
		<German>
			<Text>Karthagisches Reich:Karthagische Reich:Karthagischen Reich</Text>
			<Gender>Neuter:Neuter:Neuter</Gender>
			<Plural>0:0:0</Plural>
		</German>
		<Italian>
			<Text>Impero FRAtaginese</Text>
			<Gender>Male</Gender>
			<Plural>0</Plural>
		</Italian>
		<Spanish>
			<Text>Imperio FRAtagin&#233;s</Text>
			<Gender>Male</Gender>
			<Plural>0</Plural>
		</Spanish>
	</TEXT>
	<TEXT>
		<Tag>TXT_KEY_DN_FRA04</Tag>
		<FRAlish>Etruscan League</FRAlish>
		<French>
			<Text>Empire FRAthaginois</Text>
			<Gender>Male</Gender>
			<Plural>0</Plural>
		</French>
		<German>
			<Text>Karthagisches Reich:Karthagische Reich:Karthagischen Reich</Text>
			<Gender>Neuter:Neuter:Neuter</Gender>
			<Plural>0:0:0</Plural>
		</German>
		<Italian>
			<Text>Impero FRAtaginese</Text>
			<Gender>Male</Gender>
			<Plural>0</Plural>
		</Italian>
		<Spanish>
			<Text>Imperio FRAtagin&#233;s</Text>
			<Gender>Male</Gender>
			<Plural>0</Plural>
		</Spanish>
	</TEXT>
	<TEXT>
		<Tag>TXT_KEY_DN_FRA05</Tag>
		<FRAlish>Etruscan League</FRAlish>
		<French>
			<Text>R&#233;publique FRAthaginoise</Text>
			<Gender>Female</Gender>
			<Plural>0</Plural>
		</French>
		<German>
			<Text>Karthagische Republik:Karthagische Republik:Karthagischen Republik</Text>
			<Gender>Female:Female:Female</Gender>
			<Plural>0:0:0</Plural>
		</German>
		<Italian>
			<Text>Repubblica FRAtaginese</Text>
			<Gender>Female</Gender>
			<Plural>0</Plural>
		</Italian>
		<Spanish>
			<Text> Rep&#250;blica FRAtagin&#233;s</Text>
			<Gender>Female</Gender>
			<Plural>0</Plural>
		</Spanish>
	</TEXT>
	<TEXT>
		<Tag>TXT_KEY_DN_FRA06</Tag>
		<FRAlish>Etruscan led Italian Alliance</FRAlish>
		<French>
			<Text>Peuple de FRAthage</Text>
			<Gender>Male</Gender>
			<Plural>0</Plural>
		</French>
		<German>
			<Text>Karthagisches Volk:Karthagische Volk:Karthagischen Volk</Text>
			<Gender>Neuter:Neuter:Neuter</Gender>
			<Plural>0:0:0</Plural>
		</German>
		<Italian>
			<Text>Popolo FRAtaginese</Text>
			<Gender>Male</Gender>
			<Plural>0</Plural>
		</Italian>
		<Spanish>
			<Text>Pueblo FRAtagin&#233;s</Text>
			<Gender>Male</Gender>
			<Plural>0</Plural>
		</Spanish>
	</TEXT>
	<TEXT>
		<Tag>TXT_KEY_DN_FRA07</Tag>
		<FRAlish>Kingdom of the Ostrogoths</FRAlish>
		<French>
			<Text>Empire FRAthaginois</Text>
			<Gender>Male</Gender>
			<Plural>0</Plural>
		</French>
		<German>
			<Text>Karthagisches Reich:Karthagische Reich:Karthagischen Reich</Text>
			<Gender>Neuter:Neuter:Neuter</Gender>
			<Plural>0:0:0</Plural>
		</German>
		<Italian>
			<Text>Impero FRAtaginese</Text>
			<Gender>Male</Gender>
			<Plural>0</Plural>
		</Italian>
		<Spanish>
			<Text>Imperio FRAtagin&#233;s</Text>
			<Gender>Male</Gender>
			<Plural>0</Plural>
		</Spanish>
	</TEXT>
	<TEXT>
		<Tag>TXT_KEY_DN_FRA08</Tag>
		<FRAlish>Satrapy of Tuscony</FRAlish>
		<French>
			<Text>Califat de FRAthage</Text>
			<Gender>Male</Gender>
			<Plural>0</Plural>
		</French>
		<German>
			<Text>Kalifat von Karthago:Kalifat von Karthago:Kalifat von Karthago</Text>
			<Gender>Neuter:Neuter:Neuter</Gender>
			<Plural>0:0:0</Plural>
		</German>
		<Italian>
			<Text>Califfato di FRAtagine</Text>
			<Gender>Male</Gender>
			<Plural>0</Plural>
		</Italian>
		<Spanish>
			<Text>Califato de FRAtago</Text>
			<Gender>Male</Gender>
			<Plural>0</Plural>
		</Spanish>
	</TEXT>
	<TEXT>
		<Tag>TXT_KEY_DN_FRA09</Tag>
		<FRAlish>Roman Province of Italia</FRAlish>
		<French>
			<Text>R&#233;publique Islamique de FRAthage</Text>
			<Gender>Female</Gender>
			<Plural>0</Plural>
		</French>
		<German>
			<Text>Karthagische Republik:Karthagische Republik:Karthagischen Republik</Text>
			<Gender>Female:Female:Female</Gender>
			<Plural>0:0:0</Plural>
		</German>
		<Italian>
			<Text>Repubblica Islamica FRAtaginese</Text>
			<Gender>Female</Gender>
			<Plural>0</Plural>
		</Italian>
		<Spanish>
			<Text>Rep&#250;blica Isl&#225;mica FRAtaginesa</Text>
			<Gender>Female</Gender>
			<Plural>0</Plural>
		</Spanish>
	</TEXT>
	<TEXT>
		<Tag>TXT_KEY_DN_FRA10</Tag>
		<FRAlish>Etruscan Client Kingdom</FRAlish>
		<French>
			<Text>Satrape de FRAthage</Text>
			<Gender>Female</Gender>
			<Plural>0</Plural>
		</French>
		<German>
			<Text>Satrapie Karthago:Satrapie Karthago:Satrapie Karthago</Text>
			<Gender>Female:Female:Female</Gender>
			<Plural>0:0:0</Plural>
		</German>
		<Italian>
			<Text>Satrapia di FRAtagine</Text>
			<Gender>Female</Gender>
			<Plural>0</Plural>
		</Italian>
		<Spanish>
			<Text>Satrap&#237;a de FRAtago</Text>
			<Gender>Female</Gender>
			<Plural>0</Plural>
		</Spanish>
	</TEXT>
</Civ4GameText>
