<?xml version="1.0" encoding="ISO-8859-1"?>
<!-- edited with XMLSPY v2004 rel. 2 U (http://www.xmlspy.com) by lcollins (Firaxis Games) -->
<!-- Sid Meier's Civilization 4 -->
<!-- -->
<!-- Game Text - Unit Upgrades for Civilopedia -->
<Civ4GameText xmlns="http://www.firaxis.com">
	<TEXT>
		<Tag>TXT_KEY_LEADER_AGAMEMNON</Tag>
		<English>Agamemnon</English>
	</TEXT>
	<TEXT>
		<Tag>TXT_KEY_CIV_Mycenae_DESC</Tag>
		<English>The Mycenaens</English>
	</TEXT>
	<TEXT>
		<Tag>TXT_KEY_DN_ROM00</Tag>
		<English>Mycenae Peoples</English>
		<French>
			<Text>Peuplades Han</Text>
			<Gender>Female</Gender>
			<Plural>1</Plural>
		</French>
		<German>
			<Text>Hanv&#246;lker:Hanv&#246;lker:Hanv&#246;lkern</Text>
			<Gender>Female:Female:Female</Gender>
			<Plural>1:1:1</Plural>
		</German>
		<Italian>
			<Text>Popoli Han</Text>
			<Gender>Male</Gender>
			<Plural>1</Plural>
		</Italian>
		<Spanish>
			<Text>Pueblos Han</Text>
			<Gender>Male</Gender>
			<Plural>1</Plural>
		</Spanish>
	</TEXT>
	<TEXT>
		<Tag>TXT_KEY_DN_ROM01</Tag>
		<English>Mycenaen City States</English>
		<French>
			<Text>Pays du Milieu de ROMne</Text>
			<Gender>Male</Gender>
			<Plural>0</Plural>
		</French>
		<German>
			<Text>Reich der Mitte von ROMna:Reich der Mitte von ROMna:Reich der Mitte von ROMna</Text>
			<Gender>Neuter:Neuter:Neuter</Gender>
			<Plural>0:0:0</Plural>
		</German>
		<Italian>
			<Text>Paese di Mezzo di Cina</Text>
			<Gender>Male</Gender>
			<Plural>0</Plural>
		</Italian>
		<Spanish>
			<Text>Pa&#237;s Central de ROMna</Text>
			<Gender>Male</Gender>
			<Plural>0</Plural>
		</Spanish>
	</TEXT>
	<TEXT>
		<Tag>TXT_KEY_DN_ROM02</Tag>
		<English>Mycenaen City States</English>
		<French>
			<Text>Empire ROMnois</Text>
			<Gender>Male</Gender>
			<Plural>0</Plural>
		</French>
		<German>
			<Text>ROMnesisches Kaiserreich:ROMnesische Kaiserreich:ROMnesischen Kaiserreich</Text>
			<Gender>Neuter:Neuter:Neuter</Gender>
			<Plural>0:0:0</Plural>
		</German>
		<Italian>
			<Text>Impero Cinese</Text>
			<Gender>Male</Gender>
			<Plural>0</Plural>
		</Italian>
		<Spanish>
			<Text>Imperio ROMno</Text>
			<Gender>Male</Gender>
			<Plural>0</Plural>
		</Spanish>
	</TEXT>
	<TEXT>
		<Tag>TXT_KEY_DN_ROM03</Tag>
		<English>Mycenaen Empire</English>
		<French>
			<Text>Pays du Milieu de ROMne</Text>
			<Gender>Male</Gender>
			<Plural>0</Plural>
		</French>
		<German>
			<Text>Reich der Mitte von ROMna:Reich der Mitte von ROMna:Reich der Mitte von ROMna</Text>
			<Gender>Neuter:Neuter:Neuter</Gender>
			<Plural>0:0:0</Plural>
		</German>
		<Italian>
			<Text>Paese di Mezzo di Cina</Text>
			<Gender>Male</Gender>
			<Plural>0</Plural>
		</Italian>
		<Spanish>
			<Text>Pa&#237;s Central de ROMna</Text>
			<Gender>Male</Gender>
			<Plural>0</Plural>
		</Spanish>
	</TEXT>
	<TEXT>
		<Tag>TXT_KEY_DN_ROM04</Tag>
		<English>Mycenaen Empire</English>
		<French>
			<Text>Empire ROMnois</Text>
			<Gender>Male</Gender>
			<Plural>0</Plural>
		</French>
		<German>
			<Text>ROMnesisches Kaiserreich:ROMnesische Kaiserreich:ROMnesischen Kaiserreich</Text>
			<Gender>Neuter:Neuter:Neuter</Gender>
			<Plural>0:0:0</Plural>
		</German>
		<Italian>
			<Text>Impero Cinese</Text>
			<Gender>Male</Gender>
			<Plural>0</Plural>
		</Italian>
		<Spanish>
			<Text>Imperio ROMno</Text>
			<Gender>Male</Gender>
			<Plural>0</Plural>
		</Spanish>
	</TEXT>
	<TEXT>
		<Tag>TXT_KEY_DN_ROM05</Tag>
		<English>Thebes</English>
		<French>
			<Text>R&#233;publique de ROMne</Text>
			<Gender>Female</Gender>
			<Plural>0</Plural>
		</French>
		<German>
			<Text>Republik ROMna:Republik ROMna:Republik ROMna</Text>
			<Gender>Female:Female:Female</Gender>
			<Plural>0:0:0</Plural>
		</German>
		<Italian>
			<Text>Repubblica di Cina</Text>
			<Gender>Female</Gender>
			<Plural>0</Plural>
		</Italian>
		<Spanish>
			<Text>Rep&#250;blica de ROMna</Text>
			<Gender>Female</Gender>
			<Plural>0</Plural>
		</Spanish>
	</TEXT>
	<TEXT>
		<Tag>TXT_KEY_DN_ROM06</Tag>
		<English>Achaean League</English>
		<French>
			<Text>R&#233;publique Populaire de ROMne</Text>
			<Gender>Female</Gender>
			<Plural>0</Plural>
		</French>
		<German>
			<Text>Volksrepublik ROMna:Volksrepublik ROMna:Volksrepublik ROMna</Text>
			<Gender>Female:Female:Female</Gender>
			<Plural>0:0:0</Plural>
		</German>
		<Italian>
			<Text>Repubblica Popolare Cinese</Text>
			<Gender>Female</Gender>
			<Plural>0</Plural>
		</Italian>
		<Spanish>
			<Text>Rep&#250;blica Popular ROMna</Text>
			<Gender>Female</Gender>
			<Plural>0</Plural>
		</Spanish>
	</TEXT>
	<TEXT>
		<Tag>TXT_KEY_DN_ROM07</Tag>
		<English>Achaean League</English>
		<French>
			<Text>ROMne Nationaliste</Text>
			<Gender>Female</Gender>
			<Plural>0</Plural>
		</French>
		<German>
			<Text>Nationalistisches ROMna:Nationalistische ROMna:Nationalistischen ROMna</Text>
			<Gender>Neuter:Neuter:Neuter</Gender>
			<Plural>0:0:0</Plural>
		</German>
		<Italian>
			<Text>Cina Nazionalista</Text>
			<Gender>Female</Gender>
			<Plural>0</Plural>
		</Italian>
		<Spanish>
			<Text>ROMna Nacionalista</Text>
			<Gender>Female</Gender>
			<Plural>0</Plural>
		</Spanish>
	</TEXT>
	<TEXT>
		<Tag>TXT_KEY_DN_ROM08</Tag>
		<English>Satrapy of Korinthos</English>
		<French>
			<Text>Empire Islamique ROMnois</Text>
			<Gender>Male</Gender>
			<Plural>0</Plural>
		</French>
		<German>
			<Text>Islamisches Reich ROMna:Islamische Reich ROMna:Islamischen Reich ROMna</Text>
			<Gender>Neuter:Neuter:Neuter</Gender>
			<Plural>0:0:0</Plural>
		</German>
		<Italian>
			<Text>Impero Islamico Cinese</Text>
			<Gender>Male</Gender>
			<Plural>0</Plural>
		</Italian>
		<Spanish>
			<Text>Imperio Isl&#225;mico ROMno</Text>
			<Gender>Male</Gender>
			<Plural>0</Plural>
		</Spanish>
	</TEXT>
	<TEXT>
		<Tag>TXT_KEY_DN_ROM09</Tag>
		<English>Roman Province of Mare Aegeum</English>
		<French>
			<Text>R&#233;publique Islamique de ROMne</Text>
			<Gender>Female</Gender>
			<Plural>0</Plural>
		</French>
		<German>
			<Text>Islamische Republik ROMna:Islamische Republik ROMna:Islamischen Republik ROMna</Text>
			<Gender>Female:Female:Female</Gender>
			<Plural>0:0:0</Plural>
		</German>
		<Italian>
			<Text>Repubblica Islamica di Cina</Text>
			<Gender>Female</Gender>
			<Plural>0</Plural>
		</Italian>
		<Spanish>
			<Text>Rep&#250;blica Isl&#225;mica de ROMna</Text>
			<Gender>Female</Gender>
			<Plural>0</Plural>
		</Spanish>
	</TEXT>
	<TEXT>
		<Tag>TXT_KEY_DN_ROM10</Tag>
		<English>Mycenaen Client Kingdom</English>
		<French>
			<Text>Satrape de ROMn</Text>
			<Gender>Female</Gender>
			<Plural>0</Plural>
		</French>
		<German>
			<Text>Satrapie ROMn:Satrapie ROMn:Satrapie ROMn</Text>
			<Gender>Female:Female:Female</Gender>
			<Plural>0:0:0</Plural>
		</German>
		<Italian>
			<Text>Satrapia di ROMn</Text>
			<Gender>Female</Gender>
			<Plural>0</Plural>
		</Italian>
		<Spanish>
			<Text>Satrap&#237;a de ROMn</Text>
			<Gender>Female</Gender>
			<Plural>0</Plural>
		</Spanish>
	</TEXT>
</Civ4GameText>
